odoo8_addon_mass_mailing_statistic_extra-8.0.1.0.0.99.dev16-py2.7-nspkg.pth
odoo8_addon_mass_mailing_statistic_extra-8.0.1.0.0.99.dev16.dist-info/DESCRIPTION.rst
odoo8_addon_mass_mailing_statistic_extra-8.0.1.0.0.99.dev16.dist-info/METADATA
odoo8_addon_mass_mailing_statistic_extra-8.0.1.0.0.99.dev16.dist-info/RECORD
odoo8_addon_mass_mailing_statistic_extra-8.0.1.0.0.99.dev16.dist-info/WHEEL
odoo8_addon_mass_mailing_statistic_extra-8.0.1.0.0.99.dev16.dist-info/metadata.json
odoo8_addon_mass_mailing_statistic_extra-8.0.1.0.0.99.dev16.dist-info/namespace_packages.txt
odoo8_addon_mass_mailing_statistic_extra-8.0.1.0.0.99.dev16.dist-info/top_level.txt
odoo_addons/mass_mailing_statistic_extra/README.rst
odoo_addons/mass_mailing_statistic_extra/__init__.py
odoo_addons/mass_mailing_statistic_extra/__openerp__.py
odoo_addons/mass_mailing_statistic_extra/i18n/ca.po
odoo_addons/mass_mailing_statistic_extra/i18n/de.po
odoo_addons/mass_mailing_statistic_extra/i18n/el_GR.po
odoo_addons/mass_mailing_statistic_extra/i18n/es.po
odoo_addons/mass_mailing_statistic_extra/i18n/es_CO.po
odoo_addons/mass_mailing_statistic_extra/i18n/fi.po
odoo_addons/mass_mailing_statistic_extra/i18n/fr.po
odoo_addons/mass_mailing_statistic_extra/i18n/hr.po
odoo_addons/mass_mailing_statistic_extra/i18n/id.po
odoo_addons/mass_mailing_statistic_extra/i18n/it.po
odoo_addons/mass_mailing_statistic_extra/i18n/mass_mailing_statistic_extra.pot
odoo_addons/mass_mailing_statistic_extra/i18n/pt_BR.po
odoo_addons/mass_mailing_statistic_extra/i18n/sl.po
odoo_addons/mass_mailing_statistic_extra/models/__init__.py
odoo_addons/mass_mailing_statistic_extra/models/mail_mail.py
odoo_addons/mass_mailing_statistic_extra/models/mail_mail_statistics.py
odoo_addons/mass_mailing_statistic_extra/static/description/icon.png
odoo_addons/mass_mailing_statistic_extra/tests/__init__.py
odoo_addons/mass_mailing_statistic_extra/tests/test_mail_mail.py
odoo_addons/mass_mailing_statistic_extra/views/mass_mailing.xml
